InMemoryBackend.py
neodb-0.0.1.dist-info/LICENSE
neodb-0.0.1.dist-info/METADATA
neodb-0.0.1.dist-info/WHEEL
neodb-0.0.1.dist-info/top_level.txt
neodb-0.0.1.dist-info/RECORD
